gramps_bench/__init__.py
gramps_bench/benchmark_charts.py
gramps_bench/performance_tests.py
gramps_bench/cli/__init__.py
gramps_bench/cli/gramps_bench.py
gramps_bench/cli/gramps_bench_all.py
gramps_bench-1.0.1.dist-info/licenses/LICENSE
gramps_bench-1.0.1.dist-info/METADATA
gramps_bench-1.0.1.dist-info/WHEEL
gramps_bench-1.0.1.dist-info/entry_points.txt
gramps_bench-1.0.1.dist-info/top_level.txt
gramps_bench-1.0.1.dist-info/RECORD
