Metadata-Version: 2.4
Name: gramps-bench
Version: 1.0.1
Summary: Performance benchmarking tools for Gramps genealogy software
Home-page: https://github.com/dsblank/gramps-bench
Author: Gramps Development Team
Author-email: Gramps Development Team <gramps-devel@lists.sourceforge.net>
Maintainer-email: Gramps Development Team <gramps-devel@lists.sourceforge.net>
License: GPL-2.0-or-later
Project-URL: Homepage, https://github.com/dsblank/gramps-bench
Project-URL: Repository, https://github.com/dsblank/gramps-bench
Project-URL: Issues, https://github.com/dsblank/gramps-bench/issues
Keywords: gramps,genealogy,benchmark,performance,testing
Classifier: Development Status :: 4 - Beta
Classifier: Intended Audience :: Developers
Classifier: License :: OSI Approved :: GNU General Public License v2 or later (GPLv2+)
Classifier: Operating System :: OS Independent
Classifier: Programming Language :: Python :: 3
Classifier: Programming Language :: Python :: 3.8
Classifier: Programming Language :: Python :: 3.9
Classifier: Programming Language :: Python :: 3.10
Classifier: Programming Language :: Python :: 3.11
Classifier: Programming Language :: Python :: 3.12
Classifier: Topic :: Software Development :: Testing
Classifier: Topic :: Software Development :: Libraries :: Python Modules
Requires-Python: >=3.8
License-File: LICENSE
Requires-Dist: pytest>=6.0
Requires-Dist: pytest-benchmark>=3.4
Requires-Dist: matplotlib>=3.3
Requires-Dist: numpy>=1.19
Dynamic: author
Dynamic: home-page
Dynamic: license-file
Dynamic: requires-python
